```java

public class ClassC {

    public void fun() {
        Inner i = new Inner() {
            @Override
            public void fun() {
                System.out.println("inner");
            }
        };
        i.fun();
    }

    void println(String msg) {
        System.out.println(msg);
    }

    interface Inner {
        void fun();
    }
}

public class com.popmain.test.ClassC {
  public com.popmain.test.ClassC();
    Code:
       0: aload_0
       1: invokespecial #1                  // Method java/lang/Object."<init>":()V
       4: return

  public void fun();
    Code:
       0: new           #2                  // class com/popmain/test/ClassC$1
       3: dup
       4: aload_0
       5: invokespecial #3                  // Method com/popmain/test/ClassC$1."<init>":(Lcom/popmain/test/ClassC;)V
       8: astore_1
       9: aload_1
      10: invokeinterface #4,  1            // InterfaceMethod com/popmain/test/ClassC$Inner.fun:()V
      15: return

  void println(java.lang.String);
    Code:
       0: getstatic     #5                  // Field java/lang/System.out:Ljava/io/PrintStream;
       3: aload_1
       4: invokevirtual #6                  // Method java/io/PrintStream.println:(Ljava/lang/String;)V
       7: return
}
```

匿名内部类初始化：

```java
invokespecial #2  // Method com/popmain/test/ClassC$1."<init>":(Lcom/popmain/test/ClassC;)V
```

会把外部类实例传进去

```java
public class ClassC {

    public void fun() {
        Inner i = new InnerImpl();
        i.fun();
    }

    void println(String msg) {
        System.out.println(msg);
    }
  
    static class InnerImpl implement Inner {
        public void fun() {
          System.out.println("inner");
        }
    }

    interface Inner {
        void fun();
    }
}




public class com.popmain.test.ClassC {
  public com.popmain.test.ClassC();
    Code:
       0: aload_0
       1: invokespecial #1                  // Method java/lang/Object."<init>":()V
       4: return

  public void fun();
    Code:
       0: new           #2                  // class com/popmain/test/ClassC$InnerImpl
       3: dup
       4: invokespecial #3                  // Method com/popmain/test/ClassC$InnerImpl."<init>":()V
       7: astore_1
       8: aload_1
       9: invokeinterface #4,  1            // InterfaceMethod com/popmain/test/ClassC$Inner.fun:()V
      14: return

  void println(java.lang.String);
    Code:
       0: getstatic     #5                  // Field java/lang/System.out:Ljava/io/PrintStream;
       3: aload_1
       4: invokevirtual #6                  // Method java/io/PrintStream.println:(Ljava/lang/String;)V
       7: return
}

```

静态内部类不会传外部实例



```java
public class ClassC {

    public void fun() {
        Inner i = new InnerImpl(this) {
            @Override
            public void fun() {
                System.out.println("inner");
            }
        };
        i.fun();
    }

    void println(String msg) {
        System.out.println(msg);
    }


    static abstract class InnerImpl implements Inner {
        WeakReference<ClassC> w;
        public InnerImpl(ClassC classC) {
            w = new WeakReference<ClassC>(classC);
        }
    }

    interface Inner {
        void fun();
    }
}


public class com.popmain.test.ClassC {
  public com.popmain.test.ClassC();
    Code:
       0: aload_0
       1: invokespecial #1                  // Method java/lang/Object."<init>":()V
       4: return

  public void fun();
    Code:
       0: new           #2                  // class com/popmain/test/ClassC$1
       3: dup
       4: aload_0
       5: aload_0
       6: invokespecial #3                  // Method com/popmain/test/ClassC$1."<init>":(Lcom/popmain/test/ClassC;Lcom/popmain/test/ClassC;)V
       9: astore_1
      10: aload_1
      11: invokeinterface #4,  1            // InterfaceMethod com/popmain/test/ClassC$Inner.fun:()V
      16: return

  void println(java.lang.String);
    Code:
       0: getstatic     #5                  // Field java/lang/System.out:Ljava/io/PrintStream;
       3: aload_1
       4: invokevirtual #6                  // Method java/io/PrintStream.println:(Ljava/lang/String;)V
       7: return
}

```



即使你的内部类的构造函数参数有了外部函数的实例，匿名内部类在编译的时候还是会在构造函数中加上外部类实例的参数

```java
 invokespecial #3                  // Method com/popmain/test/ClassC$1."<init>":(Lcom/popmain/test/ClassC;Lcom/popmain/test/ClassC;)V
```

如上，我们的构造函数只有一个ClassC参数，但是实际上InnerImpl的构造函数却有两个参数